.travis.yml
CHANGES.txt
README.txt
bootstrap.py
buildout.cfg
setup.py
collective/__init__.py
collective.z3cform.wizard.egg-info/PKG-INFO
collective.z3cform.wizard.egg-info/SOURCES.txt
collective.z3cform.wizard.egg-info/dependency_links.txt
collective.z3cform.wizard.egg-info/entry_points.txt
collective.z3cform.wizard.egg-info/namespace_packages.txt
collective.z3cform.wizard.egg-info/not-zip-safe
collective.z3cform.wizard.egg-info/requires.txt
collective.z3cform.wizard.egg-info/top_level.txt
collective/z3cform/__init__.py
collective/z3cform/wizard/__init__.py
collective/z3cform/wizard/autowizard.py
collective/z3cform/wizard/configure.zcml
collective/z3cform/wizard/dynamic_wizard.txt
collective/z3cform/wizard/i18n.py
collective/z3cform/wizard/interfaces.py
collective/z3cform/wizard/tests.py
collective/z3cform/wizard/utils.py
collective/z3cform/wizard/wizard-step.pt
collective/z3cform/wizard/wizard.css
collective/z3cform/wizard/wizard.pt
collective/z3cform/wizard/wizard.py
collective/z3cform/wizard/wizard.txt
collective/z3cform/wizard/locales/collective.z3cform.wizard.pot
collective/z3cform/wizard/locales/de/LC_MESSAGES/collective.z3cform.wizard.po
collective/z3cform/wizard/locales/es/LC_MESSAGES/collective.z3cform.wizard.po
collective/z3cform/wizard/locales/fr/LC_MESSAGES/collective.z3cform.wizard.po
collective/z3cform/wizard/locales/zh_CN/LC_MESSAGES/collective.z3cform.wizard.po
docs/LICENSE.GPL
docs/LICENSE.txt