Metadata-Version: 1.1
Name: collective.z3cform.wizard
Version: 1.4.8
Summary: This is a library for creating multi-page wizards using z3c.form. Values are stored in a session until the wizard is finished.
Home-page: http://svn.plone.org/svn/collective/collective.z3cform.wizard/trunk
Author: David Glick
Author-email: davidglick@groundwire.org
License: GPL
Keywords: z3c.form wizard session
Platform: UNKNOWN
Classifier: Development Status :: 5 - Production/Stable
Classifier: Framework :: Zope2
Classifier: License :: OSI Approved :: GNU General Public License (GPL)
